rpi_intercom/__init__.py
rpi_intercom/__main__.py
rpi_intercom/circular_buffer.py
rpi_intercom/config.py
rpi_intercom/control.py
rpi_intercom/devices.py
rpi_intercom/echotest.py
rpi_intercom/install.py
rpi_intercom/intercom.py
rpi_intercom/logger.py
rpi_intercom/mumble.py
rpi_intercom/server.py
rpi_intercom/shutdown.py
rpi_intercom/sound.py
rpi_intercom/speaker.py
rpi_intercom/worker.py
rpi_intercom/static/index.html
rpi_intercom/static/script.js
rpi_intercom-0.0.19.dist-info/LICENCE
rpi_intercom-0.0.19.dist-info/METADATA
rpi_intercom-0.0.19.dist-info/WHEEL
rpi_intercom-0.0.19.dist-info/top_level.txt
rpi_intercom-0.0.19.dist-info/RECORD
