Metadata-Version: 2.1
Name: rpi-intercom
Version: 0.0.19
Summary: Intercom library for a raspberrypi
Author: Stephen Beechen
Author-email: stephen@beechens.com
License: FUCKING FREE
Classifier: Development Status :: 3 - Alpha
Classifier: Programming Language :: Python :: 3
Classifier: Programming Language :: Python :: 3.9
Requires-Python: >=3.9
License-File: LICENCE
Requires-Dist: pymumble
Requires-Dist: pyalsaaudio
Requires-Dist: gpiozero
Requires-Dist: schema
Requires-Dist: pyyaml
Requires-Dist: pyOpenSSL
Requires-Dist: numpy
Requires-Dist: psutil
Requires-Dist: aiohttp
Requires-Dist: colorlog
Requires-Dist: samplerate
Requires-Dist: aiorun
